facebookcloudapi/__init__.py
facebookcloudapi/api/__init__.py
facebookcloudapi/api/abstract/__init__.py
facebookcloudapi/api/dto/__init__.py
facebookcloudapi/api/dto/contact_object.py
facebookcloudapi/api/dto/interactive_object.py
facebookcloudapi/api/dto/location_object.py
facebookcloudapi/api/dto/message_object.py
facebookcloudapi/api/dto/template_object.py
facebookcloudapi/api/dto/text_object.py
facebookcloudapi/api/dto/inherited/__init__.py
facebookcloudapi/api/dto/inherited/action_object.py
facebookcloudapi/api/dto/inherited/address_object.py
facebookcloudapi/api/dto/inherited/body_object.py
facebookcloudapi/api/dto/inherited/button_object.py
facebookcloudapi/api/dto/inherited/email_object.py
facebookcloudapi/api/dto/inherited/footer_object.py
facebookcloudapi/api/dto/inherited/header_object.py
facebookcloudapi/api/dto/inherited/media_object.py
facebookcloudapi/api/dto/inherited/name_object.py
facebookcloudapi/api/dto/inherited/org_object.py
facebookcloudapi/api/dto/inherited/phone_object.py
facebookcloudapi/api/dto/inherited/row_object.py
facebookcloudapi/api/dto/inherited/section_object.py
facebookcloudapi/api/dto/inherited/url_object.py
facebookcloudapi/api/dto/types/__init__.py
facebookcloudapi/api/dto/types/button_type.py
facebookcloudapi/api/dto/types/contact_type.py
facebookcloudapi/api/dto/types/header_type.py
facebookcloudapi/api/dto/types/interactive_type.py
facebookcloudapi/api/dto/types/message_type.py
facebookcloudapi/api/version_v13_0/__init__.py
facebookcloudapi/utils/__init__.py
facebookcloudapi-0.0.4.dist-info/LICENSE
facebookcloudapi-0.0.4.dist-info/METADATA
facebookcloudapi-0.0.4.dist-info/WHEEL
facebookcloudapi-0.0.4.dist-info/top_level.txt
facebookcloudapi-0.0.4.dist-info/RECORD
